{"CompilerVersion": "2.0.0", "hash": "86bb2a63a6e1b4984ce64d9f00f2aec9625a8280", "entrypoint": "Main", "functions": [{"name": "get_sc", "parameters": [{"name": "pk", "type": ""}, {"name": "sign", "type": ""}, {"name": "ms", "type": ""}]}, {"name": "get_read_only_sc", "parameters": []}, {"name": "get_data", "parameters": [{"name": "key", "type": ""}]}, {"name": "save_data", "parameters": [{"name": "key", "type": ""}, {"name": "value", "type": ""}]}, {"name": "delete_data", "parameters": [{"name": "key", "type": ""}]}, {"name": "create_chat", "parameters": [{"name": "admin_a", "type": ""}, {"name": "ch_type", "type": ""}]}, {"name": "get_chat_admin", "parameters": [{"name": "member_a", "type": ""}]}, {"name": "chat_count", "parameters": []}, {"name": "add_member", "parameters": [{"name": "admin_a", "type": ""}, {"name": "member_a", "type": ""}, {"name": "ch_id", "type": ""}]}, {"name": "get_all_chat_mambers", "parameters": [{"name": "ch_id", "type": ""}]}, {"name": "my_chat_count", "parameters": [{"name": "member_a", "type": ""}]}, {"name": "my_chats", "parameters": [{"name": "member_a", "type": ""}]}, {"name": "my_chats_by_type", "parameters": [{"name": "member_a", "type": ""}, {"name": "ch_type", "type": ""}]}, {"name": "chat_type", "parameters": [{"name": "ch_id", "type": ""}]}, {"name": "set_message", "parameters": [{"name": "member_a", "type": ""}, {"name": "ch_id", "type": ""}, {"name": "message", "type": ""}]}, {"name": "get_messages", "parameters": [{"name": "member_a", "type": ""}, {"name": "ch_id", "type": ""}, {"name": "count", "type": ""}]}, {"name": "get_messages_count", "parameters": [{"name": "ch_id", "type": ""}]}, {"name": "delete_member", "parameters": [{"name": "admin_a", "type": ""}, {"name": "member_a", "type": ""}, {"name": "ch_id", "type": ""}]}, {"name": "delete_chat", "parameters": [{"name": "admin_a", "type": ""}, {"name": "ch_id", "type": ""}]}, {"name": "get_lst_messages", "parameters": [{"name": "member_a", "type": ""}]}]}